Metadata-Version: 2.4
Name: atloop
Version: 0.1.0
Summary: Tool-Integrated Task Automation Node - Automated agent for code tasks in sandbox environments
Author: atloop Team
License: Apache-2.0
Project-URL: Homepage, https://github.com/lzjever/atloop
Project-URL: Documentation, https://atloop.readthedocs.io
Project-URL: Repository, https://github.com/lzjever/atloop
Project-URL: Issues, https://github.com/lzjever/atloop/issues
Keywords: agent,automation,code-fix,sandbox,llm,ai,development-tools
Classifier: Development Status :: 3 - Alpha
Classifier: Intended Audience :: Developers
Classifier: License :: OSI Approved :: Apache Software License
Classifier: Programming Language :: Python :: 3
Classifier: Topic :: Software Development :: Libraries :: Python Modules
Classifier: Topic :: Software Development :: Testing
Requires-Python: <3.15,>=3.8
License-File: LICENSE.txt
Requires-Dist: varlord>=0.7.0
Requires-Dist: lexilux>=2.1.0
Requires-Dist: noxrunner>=2.0.0
Requires-Dist: rich>=13.0.0
Requires-Dist: json-repair>=0.30.0
Provides-Extra: dev
Requires-Dist: pytest>=7.0.0; extra == "dev"
Requires-Dist: pytest-cov>=4.0.0; extra == "dev"
Requires-Dist: ruff>=0.1.0; extra == "dev"
Requires-Dist: mypy>=1.0.0; extra == "dev"
Requires-Dist: build>=0.10.0; extra == "dev"
Provides-Extra: docs
Requires-Dist: sphinx<9.0.0,>=5.0.0; extra == "docs"
Requires-Dist: sphinx-rtd-theme>=1.0.0; extra == "docs"
Requires-Dist: furo>=2024.1.0; extra == "docs"
Requires-Dist: sphinx-autodoc-typehints>=1.19.0; extra == "docs"
Requires-Dist: sphinx-copybutton>=0.5.0; extra == "docs"
Requires-Dist: sphinx-design>=0.5.0; extra == "docs"
Dynamic: license-file
